LICENSE
README.md
pyproject.toml
setup.py
modelZoo/__init__.py
modelZoo/mbnetv2.py
modelZoo/shufflenet.py
moduleZoo/__init__.py
moduleZoo/utils.py
moduleZoo.egg-info/PKG-INFO
moduleZoo.egg-info/SOURCES.txt
moduleZoo.egg-info/dependency_links.txt
moduleZoo.egg-info/top_level.txt
moduleZoo/attention/__init__.py
moduleZoo/attention/conv_multi_head_attention.py
moduleZoo/attention/conv_self_attention.py
moduleZoo/attention/linear_multi_head_attention.py
moduleZoo/attention/utils.py
moduleZoo/convolution/__init__.py
moduleZoo/convolution/convblocks.py
moduleZoo/convolution/invertedconvblocks.py
moduleZoo/dense/__init__.py
moduleZoo/dense/denseblocks.py
moduleZoo/graphs/__init__.py
moduleZoo/graphs/grah_conv.py
moduleZoo/graphs/utils.py
moduleZoo/resblocks/__init__.py
moduleZoo/resblocks/bottleneckresidual.py
moduleZoo/resblocks/invertedresidual.py
moduleZoo/resblocks/residual.py
mzExtras/LARC.py
mzExtras/__init__.py
mzLosses/contrastive.py