Metadata-Version: 2.1
Name: moduleZoo
Version: 1.1.4
Summary: Package to host DeepLearning modules for pytorch ecosystem, to ease out model implementations.
Home-page: https://github.com/ShivamPR21/ModuleZooTorch.git
Author: Shivam Pandey
Author-email: Shivam Pandey <pandeyshivam2017robotics@gmail.com>
License:                     GNU AFFERO GENERAL PUBLIC LICENSE
Project-URL: Homepage, https://github.com/ShivamPR21/ModuleZooTorch
Keywords: DeepLearning Pytorch Modules
Classifier: Development Status :: 3 - Alpha
Classifier: Topic :: Utilities
Classifier: License :: OSI Approved :: GNU Affero General Public License v3 or later (AGPLv3+)
Requires-Python: >=3.8
License-File: LICENSE
